schedula/__init__.py
schedula/_version.py
schedula/cli.py
schedula/dispatcher.py
schedula/utils/__init__.py
schedula/utils/alg.py
schedula/utils/base.py
schedula/utils/blue.py
schedula/utils/cst.py
schedula/utils/dsp.py
schedula/utils/exc.py
schedula/utils/gen.py
schedula/utils/graph.py
schedula/utils/imp.py
schedula/utils/sol.py
schedula/utils/utl.py
schedula/utils/asy/__init__.py
schedula/utils/asy/executors.py
schedula/utils/asy/factory.py
schedula_core-1.5.78.dist-info/licenses/AUTHORS.rst
schedula_core-1.5.78.dist-info/licenses/LICENSE.txt
schedula_core-1.5.78.dist-info/METADATA
schedula_core-1.5.78.dist-info/WHEEL
schedula_core-1.5.78.dist-info/top_level.txt
schedula_core-1.5.78.dist-info/RECORD
